{
  "1": {
    "class_type": "CLIPTextEncode",
    "inputs": {"text": "PROMPT_PLACEHOLDER"}
  },
  "2": {
    "class_type": "CLIPTextEncode",
    "inputs": {"text": "NEGATIVE_PLACEHOLDER"}
  },
  "3": {
    "class_type": "CogVideoXSampler",
    "inputs": {
      "cfg": 6, "seed": 0, "steps": 50,
      "width": 720, "height": 480,
      "negative": ["2", 0], "positive": ["1", 0],
      "num_frames": 49
    }
  },
  "4": {
    "class_type": "SaveVideo",
    "inputs": {"fps": 8, "samples": ["3", 0], "filename_prefix": "cogvideo_"}
  },
  "5": {
    "class_type": "Distributed Seed",
    "inputs": {"seed": 0, "distributed_config": {}}
  },
  "6": {
    "class_type": "Distributed Collector",
    "inputs": {"images": ["4", 0], "workers": "auto"}
  }
}
